{
  "AccountNumber": "101-002-14835452-020",
  "AuthHeader": "Bearer 551cb19f4a836f950717a0202b8dde87-adad3a86ed84c81861f9b947c435220c",
  "BaseUrl": "https://api-fxpractice.oanda.com",
  "InstrumentsToMonitor": "NZD_USD|NAS100_USD|DE30_EUR|GBP_NZD|US2000_USD|EUR_GBP|EUR_USD|SG30_SGD|EU50_EUR|AUD_JPY|GBP_JPY|NATGAS_USD|XCU_USD|SUGAR_USD|AUD_CHF|EUR_CHF|GBP_USD|BCO_USD|NZD_HKD|US30_USD|NL25_EUR|XAU_USD|NZD_CAD|GBP_CHF|EUR_NZD|DE10YB_EUR|USB02Y_USD|GBP_AUD|USD_JPY|XPT_USD|EUR_JPY|CAD_CHF|NZD_JPY|CN50_USD|FR40_EUR|AUD_NZD|AUD_USD|EUR_AUD|GBP_CAD|CAD_JPY|USB10Y_USD|AUD_CAD|AU200_AUD|SPX500_USD|EUR_CAD|WHEAT_USD|UK100_GBP|USD_CAD|NZD_CHF|CAD_HKD|NZD_SGD|USD_CHF",
  "TimeFrames": "5",
  "TargetReached": false,
  "OneTrade": true,
  "RiskCalculationMode": false,
  "RiskAmount": 50.0,
  "RequiredRr": 0.4,
  "Target": 11626.0,
  "StrategyNumber": 1
}